{"_id":"order_001","elderId":"user_elder_001","elderName":"张奶奶","elderAvatar":"","elderPhone":"13812341234","elderAddress":"北京市朝阳区幸福小区3号楼","title":"需要代购蔬菜水果","description":"需要帮忙去菜市场买一些新鲜蔬菜和水果，具体清单到时候告诉您","category":"代购","serviceTime":"2026-05-18","location":{"lat":39.9042,"lng":116.4074},"address":"北京市朝阳区幸福小区3号楼","urgency":3,"volunteerId":"user_vol_001","volunteerName":"李志愿","status":"completed","rating":5,"comment":"非常热心，买的东西很新鲜","checkInTime":{"$date":"2026-05-10T09:00:00.000Z"},"checkOutTime":{"$date":"2026-05-10T11:30:00.000Z"},"serviceHours":2.5,"createTime":{"$date":"2026-05-08T08:00:00.000Z"},"updateTime":{"$date":"2026-05-10T11:30:00.000Z"},"acceptTime":{"$date":"2026-05-09T08:00:00.000Z"},"completeTime":{"$date":"2026-05-10T11:30:00.000Z"}}
{"_id":"order_002","elderId":"user_elder_002","elderName":"王大爷","elderAvatar":"","elderPhone":"13798765432","elderAddress":"北京市海淀区阳光花园1号楼","title":"陪同就医看心内科","description":"需要志愿者陪同去医院心内科做例行检查，帮忙挂号取药","category":"就医陪同","serviceTime":"2026-05-20","location":{"lat":39.9842,"lng":116.3074},"address":"北京市海淀区阳光花园1号楼","urgency":4,"volunteerId":"","volunteerName":"","status":"pending","rating":0,"comment":"","checkInTime":null,"checkOutTime":null,"serviceHours":0,"createTime":{"$date":"2026-05-15T08:00:00.000Z"},"updateTime":{"$date":"2026-05-15T08:00:00.000Z"},"acceptTime":null,"completeTime":null}
{"_id":"order_003","elderId":"user_elder_001","elderName":"张奶奶","elderAvatar":"","elderPhone":"13812341234","elderAddress":"北京市朝阳区幸福小区3号楼","title":"家务帮忙打扫卫生","description":"家里需要做大扫除，擦窗户拖地整理","category":"家务帮忙","serviceTime":"2026-05-22","location":{"lat":39.9042,"lng":116.4074},"address":"北京市朝阳区幸福小区3号楼","urgency":2,"volunteerId":"user_vol_002","volunteerName":"赵小明","status":"accepted","rating":0,"comment":"","checkInTime":null,"checkOutTime":null,"serviceHours":0,"createTime":{"$date":"2026-05-14T08:00:00.000Z"},"updateTime":{"$date":"2026-05-15T08:00:00.000Z"},"acceptTime":{"$date":"2026-05-15T09:00:00.000Z"},"completeTime":null}
{"_id":"order_004","elderId":"user_elder_003","elderName":"刘阿姨","elderAvatar":"","elderPhone":"13687654321","elderAddress":"北京市西城区和平里8号","title":"上门陪伴聊天","description":"一个人在家比较孤独，希望有年轻人来陪我聊聊天","category":"日常聊天","serviceTime":"2026-05-19","location":{"lat":39.9342,"lng":116.3874},"address":"北京市西城区和平里8号","urgency":2,"volunteerId":"user_vol_001","volunteerName":"李志愿","status":"in_progress","rating":0,"comment":"","checkInTime":{"$date":"2026-05-16T14:00:00.000Z"},"checkOutTime":null,"serviceHours":0,"createTime":{"$date":"2026-05-13T08:00:00.000Z"},"updateTime":{"$date":"2026-05-16T14:00:00.000Z"},"acceptTime":{"$date":"2026-05-14T10:00:00.000Z"},"completeTime":null}
{"_id":"order_005","elderId":"user_elder_002","elderName":"王大爷","elderAvatar":"","elderPhone":"13798765432","elderAddress":"北京市海淀区阳光花园1号楼","title":"代购日用品","description":"需要帮忙买一些日用品，牙膏、洗衣液等","category":"代购","serviceTime":"2026-05-16","location":{"lat":39.9842,"lng":116.3074},"address":"北京市海淀区阳光花园1号楼","urgency":1,"volunteerId":"user_vol_002","volunteerName":"赵小明","status":"completed","rating":4,"comment":"服务很好","checkInTime":{"$date":"2026-05-16T10:00:00.000Z"},"checkOutTime":{"$date":"2026-05-16T11:00:00.000Z"},"serviceHours":1,"createTime":{"$date":"2026-05-12T08:00:00.000Z"},"updateTime":{"$date":"2026-05-16T11:00:00.000Z"},"acceptTime":{"$date":"2026-05-13T08:00:00.000Z"},"completeTime":{"$date":"2026-05-16T11:00:00.000Z"}}
